{
  "name": "hegemony_energy_comparison",
  "description": "Screenshot deck experiment for comparing Hegemony energy timing and amount.",
  "deckFile": "../simulation_decks/regent_screenshot_hegemony_energy_approx.json",
  "options": {
    "turns": 8,
    "runs": 1000,
    "seed": 1,
    "handSize": 5,
    "baseEnergy": 3,
    "baseStars": 0,
    "starsPersistBetweenTurns": false,
    "maxCardsPlayedPerTurn": 16,
    "maxBranchingCards": 8,
    "pmfBucketSize": 1
  },
  "variants": [
    {
      "id": "original_next_turn_2",
      "label": "Original Hegemony: +2 energy next turn",
      "cardPatches": [
        {
          "matchTypeName": "Hegemony",
          "patch": {
            "energyGain": 0,
            "energyNextTurn": 2
          }
        }
      ]
    },
    {
      "id": "next_turn_1",
      "label": "Modified Hegemony: +1 energy next turn",
      "cardPatches": [
        {
          "matchTypeName": "Hegemony",
          "patch": {
            "energyGain": 0,
            "energyNextTurn": 1
          }
        }
      ]
    },
    {
      "id": "this_turn_1",
      "label": "Modified Hegemony: +1 energy this turn",
      "cardPatches": [
        {
          "matchTypeName": "Hegemony",
          "patch": {
            "energyGain": 1,
            "energyNextTurn": 0
          }
        }
      ]
    },
    {
      "id": "this_turn_2",
      "label": "Modified Hegemony: +2 energy this turn",
      "cardPatches": [
        {
          "matchTypeName": "Hegemony",
          "patch": {
            "energyGain": 2,
            "energyNextTurn": 0
          }
        }
      ]
    }
  ],
  "assumptions": [
    "Deltas are local to this deck, simulator policy, run count, and turn horizon."
  ]
}
